blue_backup.py
blue_backup-1.0.dist-info/licenses/LICENSE
blue_backup-1.0.dist-info/METADATA
blue_backup-1.0.dist-info/WHEEL
blue_backup-1.0.dist-info/entry_points.txt
blue_backup-1.0.dist-info/top_level.txt
blue_backup-1.0.dist-info/RECORD
