Metadata-Version: 2.4
Name: blue-backup
Version: 1.0
Summary: A backup utility based on snapshots and rsync.
Author-email: Udi Fuchs <udifuchs@gmail.com>
License-Expression: MIT
Project-URL: Homepage, http://github.com/udifuchs/blue-backup
Keywords: backup
Classifier: Development Status :: 5 - Production/Stable
Classifier: Environment :: Console
Classifier: Operating System :: POSIX
Classifier: Programming Language :: Python :: 3 :: Only
Classifier: Programming Language :: Python :: 3.8
Classifier: Programming Language :: Python :: 3.9
Classifier: Programming Language :: Python :: 3.10
Classifier: Programming Language :: Python :: 3.11
Classifier: Programming Language :: Python :: 3.12
Classifier: Programming Language :: Python :: 3.13
Classifier: Programming Language :: Python :: 3.14
Classifier: Topic :: System :: Archiving :: Backup
Requires-Python: >=3.8
License-File: LICENSE
Requires-Dist: tomli; python_version < "3.11"
Requires-Dist: paramiko
Dynamic: license-file
